{"chunk_definitions":[{"chunk_id":"csetup_chunk","chunk_label":"setup","document_id":"43492470","expansion_state":0,"options":{"engine":"r","include":false,"label":"setup"},"row":26,"row_count":1,"visible":true},{"chunk_id":"ceqk3t21ptq0x","chunk_label":"data1","document_id":"43492470","expansion_state":0,"options":{"engine":"r","label":"data1"},"row":35,"row_count":1,"visible":true},{"chunk_id":"c0wtwtq0nwfgm","chunk_label":"ans1","document_id":"43492470","expansion_state":0,"options":{"engine":"r","label":"ans1"},"row":42,"row_count":1,"visible":true},{"chunk_id":"cmzarvip511pi","chunk_label":"unnamed-chunk-1","document_id":"43492470","expansion_state":0,"options":{"engine":"r","label":"unnamed-chunk-216"},"row":47,"row_count":1,"visible":true},{"chunk_id":"c008je0ss1qq1","chunk_label":"data2","document_id":"43492470","expansion_state":0,"options":{"engine":"r","label":"data2"},"row":53,"row_count":1,"visible":true},{"chunk_id":"cjkh72wue6z5v","chunk_label":"ans21","document_id":"43492470","expansion_state":0,"options":{"engine":"r","label":"ans21"},"row":64,"row_count":1,"visible":true},{"chunk_id":"cv0ebg6njpm15","chunk_label":"unnamed-chunk-2","document_id":"43492470","expansion_state":0,"options":{"engine":"r","label":"unnamed-chunk-217"},"row":70,"row_count":1,"visible":true},{"chunk_id":"cffq66m8lxyqt","chunk_label":"ans22","document_id":"43492470","expansion_state":0,"options":{"engine":"r","label":"ans22"},"row":84,"row_count":1,"visible":true},{"chunk_id":"cmnw8yzzvtds1","chunk_label":"ans23","document_id":"43492470","expansion_state":0,"options":{"engine":"r","label":"ans23"},"row":97,"row_count":1,"visible":true},{"chunk_id":"c1i2lofopxq4o","chunk_label":"ans24","document_id":"43492470","expansion_state":0,"options":{"engine":"r","label":"ans24"},"row":106,"row_count":1,"visible":true}],"doc_write_time":1590500830}