{"chunk_definitions":[{"chunk_id":"csetup_chunk","chunk_label":"setup","document_id":"F1FAF9F1","expansion_state":0,"options":{"engine":"r","include":false,"label":"setup"},"row":9,"row_count":1,"visible":true},{"chunk_id":"cy5fzus9uc4fs","chunk_label":"unnamed-chunk-1","document_id":"F1FAF9F1","expansion_state":0,"options":{"engine":"r","label":"unnamed-chunk-146"},"row":13,"row_count":1,"visible":true},{"chunk_id":"c97noami155nw","chunk_label":"unnamed-chunk-2","document_id":"F1FAF9F1","expansion_state":0,"options":{"engine":"r","label":"unnamed-chunk-149"},"row":27,"row_count":1,"visible":true},{"chunk_id":"cpx4xjo1veqkb","chunk_label":"unnamed-chunk-3","document_id":"F1FAF9F1","expansion_state":0,"options":{"engine":"r","label":"unnamed-chunk-154"},"row":44,"row_count":1,"visible":true},{"chunk_id":"c3m1tjj789v4q","chunk_label":"unnamed-chunk-4","document_id":"F1FAF9F1","expansion_state":0,"options":{"engine":"r","label":"unnamed-chunk-155"},"row":51,"row_count":1,"visible":true},{"chunk_id":"c5yusqo452y2o","chunk_label":"unnamed-chunk-5","document_id":"7A39A67C","expansion_state":0,"options":{"engine":"r","label":"unnamed-chunk-156"},"row":58,"row_count":1,"visible":true},{"chunk_id":"cgbn9qw0rmhu8","chunk_label":"unnamed-chunk-6","document_id":"F1FAF9F1","expansion_state":0,"options":{"engine":"r","label":"unnamed-chunk-157"},"row":64,"row_count":1,"visible":true},{"chunk_id":"ckyhzmf7tgxgn","chunk_label":"unnamed-chunk-7","document_id":"F1FAF9F1","expansion_state":0,"options":{"engine":"r","label":"unnamed-chunk-158"},"row":75,"row_count":1,"visible":true},{"chunk_id":"cfhokrw9bdb0q","chunk_label":"unnamed-chunk-8","document_id":"F1FAF9F1","expansion_state":0,"options":{"engine":"r","label":"unnamed-chunk-159"},"row":81,"row_count":1,"visible":true},{"chunk_id":"cyrglay3pvaq4","chunk_label":"unnamed-chunk-9","document_id":"F1FAF9F1","expansion_state":0,"options":{"engine":"r","label":"unnamed-chunk-160"},"row":90,"row_count":1,"visible":true},{"chunk_id":"ch6mv8q7tn64r","chunk_label":"unnamed-chunk-10","document_id":"F1FAF9F1","expansion_state":0,"options":{"engine":"r","label":"unnamed-chunk-161"},"row":105,"row_count":1,"visible":true},{"chunk_id":"c9hum5ctis5qg","chunk_label":"unnamed-chunk-11","document_id":"F1FAF9F1","expansion_state":0,"options":{"engine":"r","label":"unnamed-chunk-162"},"row":127,"row_count":1,"visible":true},{"chunk_id":"cnkmln87q3qnw","chunk_label":"unnamed-chunk-12","document_id":"F1FAF9F1","expansion_state":0,"options":{"engine":"r","label":"unnamed-chunk-163"},"row":139,"row_count":1,"visible":true},{"chunk_id":"c7zqh9hhqee1x","chunk_label":"unnamed-chunk-13","document_id":"F1FAF9F1","expansion_state":0,"options":{"engine":"r","label":"unnamed-chunk-164"},"row":149,"row_count":1,"visible":true},{"chunk_id":"cwqdofojae5s9","chunk_label":"unnamed-chunk-14","document_id":"F1FAF9F1","expansion_state":0,"options":{"engine":"r","label":"unnamed-chunk-169"},"row":159,"row_count":1,"visible":true},{"chunk_id":"c2an8dh3n1eqx","chunk_label":"unnamed-chunk-15","document_id":"F1FAF9F1","expansion_state":0,"options":{"engine":"r","label":"unnamed-chunk-170"},"row":167,"row_count":1,"visible":true},{"chunk_id":"cjnyzld8wpjdk","chunk_label":"unnamed-chunk-16","document_id":"F1FAF9F1","expansion_state":0,"options":{"engine":"r","label":"unnamed-chunk-171"},"row":182,"row_count":1,"visible":true},{"chunk_id":"c3coz83aji94g","chunk_label":"unnamed-chunk-17","document_id":"F1FAF9F1","expansion_state":0,"options":{"engine":"r","label":"unnamed-chunk-172"},"row":188,"row_count":1,"visible":true},{"chunk_id":"c5mnrlv6wxlol","chunk_label":"unnamed-chunk-18","document_id":"F1FAF9F1","expansion_state":0,"options":{"engine":"r","label":"unnamed-chunk-173"},"row":203,"row_count":1,"visible":true},{"chunk_id":"cua1u0ny6iii4","chunk_label":"unnamed-chunk-19","document_id":"F1FAF9F1","expansion_state":0,"options":{"engine":"r","label":"unnamed-chunk-174"},"row":210,"row_count":1,"visible":true},{"chunk_id":"ck98tgcp4kuwl","chunk_label":"unnamed-chunk-20","document_id":"F1FAF9F1","expansion_state":0,"options":{"engine":"r","label":"unnamed-chunk-178"},"row":218,"row_count":1,"visible":true},{"chunk_id":"cxswszaguqwqt","chunk_label":"unnamed-chunk-21","document_id":"F1FAF9F1","expansion_state":0,"options":{"engine":"r","label":"unnamed-chunk-179"},"row":233,"row_count":1,"visible":true},{"chunk_id":"cq1hb4l8ss4yk","chunk_label":"unnamed-chunk-22","document_id":"F1FAF9F1","expansion_state":0,"options":{"engine":"r","label":"unnamed-chunk-180"},"row":242,"row_count":1,"visible":true},{"chunk_id":"ce8qtiz2pxb1x","chunk_label":"unnamed-chunk-23","document_id":"F1FAF9F1","expansion_state":0,"options":{"engine":"r","label":"unnamed-chunk-181"},"row":250,"row_count":1,"visible":true},{"chunk_id":"coo8a8ht9jy4u","chunk_label":"unnamed-chunk-24","document_id":"F1FAF9F1","expansion_state":0,"options":{"engine":"r","label":"unnamed-chunk-182"},"row":258,"row_count":1,"visible":true},{"chunk_id":"c04wuiurqehzv","chunk_label":"unnamed-chunk-25","document_id":"F1FAF9F1","expansion_state":0,"options":{"engine":"r","label":"unnamed-chunk-183"},"row":266,"row_count":1,"visible":true},{"chunk_id":"c7efxxomqok8m","chunk_label":"unnamed-chunk-26","document_id":"F1FAF9F1","expansion_state":0,"options":{"engine":"r","label":"unnamed-chunk-187"},"row":311,"row_count":1,"visible":true},{"chunk_id":"cvzutzka6upcx","chunk_label":"unnamed-chunk-27","document_id":"F1FAF9F1","expansion_state":0,"options":{"engine":"r","label":"unnamed-chunk-188"},"row":320,"row_count":1,"visible":true},{"chunk_id":"cbha2pps2fc12","chunk_label":"unnamed-chunk-28","document_id":"F1FAF9F1","expansion_state":0,"options":{"engine":"r","label":"unnamed-chunk-189"},"row":324,"row_count":1,"visible":true},{"chunk_id":"cwmanxlgdwuwz","chunk_label":"unnamed-chunk-29","document_id":"7A39A67C","expansion_state":0,"options":{"engine":"r","label":"unnamed-chunk-190"},"row":332,"row_count":1,"visible":true},{"chunk_id":"cx3i49j15br6g","chunk_label":"unnamed-chunk-30","document_id":"7A39A67C","expansion_state":0,"options":{"engine":"r","label":"unnamed-chunk-191"},"row":345,"row_count":1,"visible":true},{"chunk_id":"ccugcq0343ep6","chunk_label":"unnamed-chunk-31","document_id":"7A39A67C","expansion_state":0,"options":{"engine":"r","label":"unnamed-chunk-193"},"row":354,"row_count":1,"visible":true},{"chunk_id":"c1dmv9rqkl81o","chunk_label":"unnamed-chunk-32","document_id":"7A39A67C","expansion_state":0,"options":{"engine":"r","label":"unnamed-chunk-195"},"row":362,"row_count":1,"visible":true},{"chunk_id":"cfnk1z82iuk9w","chunk_label":"unnamed-chunk-33","document_id":"7A39A67C","expansion_state":0,"options":{"engine":"r","label":"unnamed-chunk-196"},"row":369,"row_count":1,"visible":true},{"chunk_id":"crw2ccxx6dwsy","chunk_label":"unnamed-chunk-34","document_id":"7A39A67C","expansion_state":0,"options":{"engine":"r","label":"unnamed-chunk-197"},"row":398,"row_count":1,"visible":true}],"doc_write_time":1589348434}